{
    "resourceType": "ValueSet",
    "id": "dicom-cid-3527",
    "url": "http://hl7.org/fhir/uv/dicom-terminology/ValueSet/dicom-cid-3527",
    "identifier": [
        {
            "system": "urn:ietf:rfc:3986",
            "value": "urn:oid:1.2.840.10008.6.1.141"
        }
    ],
    "version": "20030327",
    "name": "BloodBaseExcess",
    "status": "active",
    "experimental": false,
    "date": "2025-04-11",
    "publisher": "NEMA MITA DICOM",
    "description": "Transitive closure of CID 3527 BloodBaseExcess",
    "copyright": "\u00a9 2025 NEMA",
    "compose": {
        "include": [
            {
                "system": "http://loinc.org",
                "concept": [
                    {
                        "code": "11555-0",
                        "display": "Blood Base Excess"
                    },
                    {
                        "code": "1927-3",
                        "display": "Venous Blood Base Excess"
                    },
                    {
                        "code": "1925-7",
                        "display": "Arterial Blood Base Excess"
                    }
                ]
            }
        ]
    },
    "title": "BloodBaseExcess",
    "versionAlgorithmCoding": {
        "system": "http://hl7.org/fhir/version-algorithm",
        "code": "date",
        "display": "Date"
    }
}