{
  "resourceType": "ValueSet",
  "status": "draft",
  "name": "ECGLeadNoiseDescription",
  "id": "dicom-cid-3680-ECGLeadNoiseDescription",
  "description": "Codes reprinted by permission of IEEE, Copyright 2004 by IEEE. ISO/IEEE 11073-10102 available through",
  "url": "http://hl7.org/fhir/uv/dicom-terminology/ValueSet/dicom-cid-3680-ECGLeadNoiseDescription",
  "identifier": [
    {
      "system": "urn:ietf:rfc:3986",
      "value": "urn:oid:1.2.840.10008.6.1.194"
    }
  ],
  "version": "20110330",
  "title": "ECG Lead Noise Description",
  "compose": {
    "include": [
      {
        "system": "urn:iso:std:iso:11073:10101",
        "concept": [
          {
            "code": "10:11200",
            "display": "No noise"
          },
          {
            "code": "10:11216",
            "display": "Moderate noise"
          },
          {
            "code": "10:11232",
            "display": "Severe noise"
          },
          {
            "code": "10:11248",
            "display": "No signal"
          }
        ]
      }
    ]
  }
}
