{
    "resourceType": "ValueSet",
    "id": "dicom-cid-12309",
    "url": "http://hl7.org/fhir/uv/dicom-terminology/ValueSet/dicom-cid-12309",
    "identifier": [
        {
            "system": "urn:ietf:rfc:3986",
            "value": "urn:oid:1.2.840.10008.6.1.1426"
        }
    ],
    "version": "20211112",
    "name": "CoreEchoStrainMeasurement",
    "status": "active",
    "experimental": false,
    "date": "2025-04-11",
    "publisher": "NEMA MITA DICOM",
    "description": "Transitive closure of CID 12309 CoreEchoStrainMeasurement",
    "copyright": "\u00a9 2025 NEMA",
    "compose": {
        "include": [
            {
                "system": "http://dicom.nema.org/resources/ontology/DCM",
                "concept": [
                    {
                        "code": "130692",
                        "display": "LV Peak Systolic GLS 2CH (Endocardial)"
                    },
                    {
                        "code": "130691",
                        "display": "LV Peak Systolic GLS 4CH (Endocardial)"
                    },
                    {
                        "code": "130690",
                        "display": "LV Peak Systolic GLS Multiview Mean (Endocardial)"
                    },
                    {
                        "code": "130696",
                        "display": "LV Peak GLS 2CH (Endocardial)"
                    },
                    {
                        "code": "130695",
                        "display": "LV Peak GLS 4CH (Endocardial)"
                    },
                    {
                        "code": "130694",
                        "display": "LV Peak GLS Multiview Mean (Endocardial)"
                    },
                    {
                        "code": "130693",
                        "display": "LV Peak Systolic GLS ALAX (Endocardial)"
                    },
                    {
                        "code": "130689",
                        "display": "LV End-systolic GLS ALAX (Endocardial)"
                    },
                    {
                        "code": "130688",
                        "display": "LV End-systolic GLS 2CH (Endocardial)"
                    },
                    {
                        "code": "130687",
                        "display": "LV End-systolic GLS 4CH (Endocardial)"
                    },
                    {
                        "code": "130698",
                        "display": "LV End-systolic Mechanical Dispersion"
                    },
                    {
                        "code": "130686",
                        "display": "LV End-systolic GLS Multiview Mean (Endocardial)"
                    },
                    {
                        "code": "130697",
                        "display": "LV Peak GLS ALAX (Endocardial)"
                    }
                ]
            }
        ]
    },
    "title": "CoreEchoStrainMeasurement",
    "versionAlgorithmCoding": {
        "system": "http://hl7.org/fhir/version-algorithm",
        "code": "date",
        "display": "Date"
    }
}